maticinfos-0.2.dist-info/DESCRIPTION.rst
maticinfos-0.2.dist-info/METADATA
maticinfos-0.2.dist-info/RECORD
maticinfos-0.2.dist-info/WHEEL
maticinfos-0.2.dist-info/metadata.json
maticinfos-0.2.dist-info/top_level.txt
toolsbasematic/__init__.py
toolsbasematic/reader.py
